ipa_deploy/__init__.py
ipa_deploy/version.py
ipa_deploy-2.0.1.dist-info/METADATA
ipa_deploy-2.0.1.dist-info/WHEEL
ipa_deploy-2.0.1.dist-info/entry_points.txt
ipa_deploy-2.0.1.dist-info/top_level.txt
ipa_deploy-2.0.1.dist-info/RECORD
